{
  "version": "5.10.1",
  "flags": {},
  "shapes": [
    {
      "label": "body",
      "points": [
        [
          375.0,
          725.5
        ],
        [
          356.0,
          725.5
        ],
        [
          348.0,
          721.5
        ],
        [
          337.5,
          710.0
        ],
        [
          333.0,
          691.5
        ],
        [
          300.0,
          684.5
        ],
        [
          282.0,
          675.5
        ],
        [
          272.5,
          665.0
        ],
        [
          274.5,
          650.0
        ],
        [
          280.0,
          640.5
        ],
        [
          311.0,
          642.5
        ],
        [
          335.0,
          637.5
        ],
        [
          338.5,
          641.0
        ],
        [
          341.5,
          635.0
        ],
        [
          340.5,
          618.0
        ],
        [
          344.5,
          591.0
        ],
        [
          365.5,
          563.0
        ],
        [
          373.5,
          545.0
        ],
        [
          362.5,
          517.0
        ],
        [
          357.0,
          510.5
        ],
        [
          344.0,
          511.5
        ],
        [
          317.0,
          532.5
        ],
        [
          309.5,
          528.0
        ],
        [
          303.5,
          515.0
        ],
        [
          308.5,
          488.0
        ],
        [
          295.5,
          479.0
        ],
        [
          289.5,
          467.0
        ],
        [
          295.5,
          458.0
        ],
        [
          272.5,
          407.0
        ],
        [
          279.5,
          395.0
        ],
        [
          290.0,
          387.5
        ],
        [
          312.5,
          385.0
        ],
        [
          307.5,
          357.0
        ],
        [
          298.5,
          348.0
        ],
        [
          289.5,
          327.0
        ],
        [
          286.5,
          291.0
        ],
        [
          292.5,
          270.0
        ],
        [
          308.5,
          246.0
        ],
        [
          322.0,
          233.5
        ],
        [
          341.0,
          223.5
        ],
        [
          358.0,
          219.5
        ],
        [
          400.0,
          224.5
        ],
        [
          421.0,
          236.5
        ],
        [
          435.5,
          250.0
        ],
        [
          449.5,
          279.0
        ],
        [
          453.5,
          328.0
        ],
        [
          469.0,
          333.5
        ],
        [
          474.5,
          345.0
        ],
        [
          539.5,
          411.0
        ],
        [
          567.5,
          468.0
        ],
        [
          578.5,
          513.0
        ],
        [
          578.5,
          557.0
        ],
        [
          574.5,
          590.0
        ],
        [
          564.5,
          617.0
        ],
        [
          547.5,
          640.0
        ],
        [
          518.0,
          660.5
        ],
        [
          485.0,
          670.5
        ],
        [
          455.0,
          666.5
        ],
        [
          437.0,
          653.5
        ],
        [
          434.5,
          662.0
        ],
        [
          428.0,
          661.5
        ],
        [
          426.5,
          664.0
        ],
        [
          432.5,
          692.0
        ],
        [
          428.5,
          709.0
        ],
        [
          408.0,
          719.5
        ],
        [
          401.0,
          718.5
        ],
        [
          398.0,
          721.5
        ]
      ],
      "group_id": null,
      "description": "",
      "shape_type": "polygon",
      "flags": {},
      "mask": null
    },
    {
      "label": "head",
      "points": [
        [
          348.0,
          408.5
        ],
        [
          344.0,
          407.5
        ],
        [
          341.0,
          408.5
        ],
        [
          329.0,
          403.5
        ],
        [
          324.5,
          400.0
        ],
        [
          323.0,
          396.5
        ],
        [
          321.0,
          396.5
        ],
        [
          318.5,
          394.0
        ],
        [
          318.5,
          392.0
        ],
        [
          315.5,
          387.0
        ],
        [
          313.5,
          386.0
        ],
        [
          314.5,
          383.0
        ],
        [
          312.5,
          380.0
        ],
        [
          311.5,
          366.0
        ],
        [
          298.5,
          349.0
        ],
        [
          289.5,
          329.0
        ],
        [
          288.5,
          313.0
        ],
        [
          287.5,
          312.0
        ],
        [
          288.5,
          300.0
        ],
        [
          287.5,
          299.0
        ],
        [
          288.5,
          296.0
        ],
        [
          290.0,
          294.5
        ],
        [
          292.0,
          294.5
        ],
        [
          295.5,
          290.0
        ],
        [
          289.5,
          287.0
        ],
        [
          289.5,
          282.0
        ],
        [
          292.5,
          273.0
        ],
        [
          292.5,
          269.0
        ],
        [
          295.5,
          266.0
        ],
        [
          298.5,
          259.0
        ],
        [
          302.5,
          257.0
        ],
        [
          304.5,
          252.0
        ],
        [
          309.5,
          245.0
        ],
        [
          311.0,
          243.5
        ],
        [
          313.0,
          243.5
        ],
        [
          314.0,
          241.5
        ],
        [
          316.0,
          241.5
        ],
        [
          316.5,
          239.0
        ],
        [
          320.0,
          235.5
        ],
        [
          323.0,
          233.5
        ],
        [
          326.0,
          234.5
        ],
        [
          329.0,
          231.5
        ],
        [
          331.0,
          231.5
        ],
        [
          332.0,
          229.5
        ],
        [
          335.0,
          229.5
        ],
        [
          341.0,
          224.5
        ],
        [
          345.0,
          224.5
        ],
        [
          348.0,
          222.5
        ],
        [
          351.0,
          222.5
        ],
        [
          353.0,
          220.5
        ],
        [
          364.0,
          220.5
        ],
        [
          365.0,
          219.5
        ],
        [
          367.0,
          220.5
        ],
        [
          370.0,
          219.5
        ],
        [
          372.0,
          220.5
        ],
        [
          379.0,
          220.5
        ],
        [
          386.0,
          223.5
        ],
        [
          390.0,
          223.5
        ],
        [
          395.0,
          225.5
        ],
        [
          401.0,
          225.5
        ],
        [
          407.0,
          231.5
        ],
        [
          413.0,
          232.5
        ],
        [
          419.0,
          238.5
        ],
        [
          422.0,
          238.5
        ],
        [
          438.5,
          256.0
        ],
        [
          445.5,
          268.0
        ],
        [
          447.5,
          278.0
        ],
        [
          449.5,
          280.0
        ],
        [
          450.5,
          292.0
        ],
        [
          452.5,
          299.0
        ],
        [
          452.5,
          324.0
        ],
        [
          447.0,
          326.5
        ],
        [
          444.0,
          329.5
        ],
        [
          429.0,
          333.5
        ],
        [
          424.0,
          336.5
        ],
        [
          411.0,
          338.5
        ],
        [
          398.5,
          351.0
        ],
        [
          389.5,
          362.0
        ],
        [
          389.5,
          364.0
        ],
        [
          384.5,
          370.0
        ],
        [
          380.5,
          379.0
        ],
        [
          375.5,
          386.0
        ],
        [
          371.5,
          396.0
        ],
        [
          369.5,
          397.0
        ],
        [
          367.5,
          401.0
        ],
        [
          358.0,
          407.5
        ],
        [
          349.0,
          407.5
        ]
      ],
      "group_id": null,
      "description": "",
      "shape_type": "polygon",
      "flags": {},
      "mask": null
    },
    {
      "label": "hand",
      "points": [
        [
          299.0,
          456.5
        ],
        [
          294.0,
          456.5
        ],
        [
          292.5,
          455.0
        ],
        [
          292.5,
          453.0
        ],
        [
          291.5,
          452.0
        ],
        [
          291.5,
          451.0
        ],
        [
          289.5,
          449.0
        ],
        [
          289.5,
          447.0
        ],
        [
          288.5,
          446.0
        ],
        [
          288.5,
          445.0
        ],
        [
          286.5,
          442.0
        ],
        [
          286.5,
          440.0
        ],
        [
          284.5,
          438.0
        ],
        [
          284.5,
          437.0
        ],
        [
          283.5,
          436.0
        ],
        [
          283.5,
          435.0
        ],
        [
          282.5,
          434.0
        ],
        [
          282.5,
          433.0
        ],
        [
          280.5,
          431.0
        ],
        [
          280.5,
          429.0
        ],
        [
          279.5,
          428.0
        ],
        [
          279.5,
          426.0
        ],
        [
          278.5,
          425.0
        ],
        [
          278.5,
          424.0
        ],
        [
          277.5,
          423.0
        ],
        [
          277.5,
          422.0
        ],
        [
          274.5,
          419.0
        ],
        [
          274.5,
          417.0
        ],
        [
          273.5,
          416.0
        ],
        [
          273.5,
          414.0
        ],
        [
          272.5,
          413.0
        ],
        [
          272.5,
          410.0
        ],
        [
          271.5,
          409.0
        ],
        [
          271.5,
          404.0
        ],
        [
          273.5,
          402.0
        ],
        [
          273.5,
          401.0
        ],
        [
          275.5,
          399.0
        ],
        [
          275.5,
          398.0
        ],
        [
          277.0,
          396.5
        ],
        [
          278.0,
          396.5
        ],
        [
          279.0,
          394.5
        ],
        [
          280.0,
          394.5
        ],
        [
          285.0,
          389.5
        ],
        [
          286.0,
          389.5
        ],
        [
          288.0,
          387.5
        ],
        [
          289.0,
          387.5
        ],
        [
          290.0,
          386.5
        ],
        [
          292.0,
          386.5
        ],
        [
          293.0,
          385.5
        ],
        [
          295.0,
          385.5
        ],
        [
          296.0,
          384.5
        ],
        [
          306.0,
          384.5
        ],
        [
          308.0,
          386.5
        ],
        [
          312.0,
          386.5
        ],
        [
          313.0,
          387.5
        ],
        [
          314.0,
          387.5
        ],
        [
          318.5,
          392.0
        ],
        [
          318.5,
          393.0
        ],
        [
          320.5,
          395.0
        ],
        [
          320.5,
          396.0
        ],
        [
          321.5,
          397.0
        ],
        [
          321.5,
          398.0
        ],
        [
          322.5,
          399.0
        ],
        [
          322.5,
          400.0
        ],
        [
          323.5,
          401.0
        ],
        [
          323.5,
          402.0
        ],
        [
          324.5,
          403.0
        ],
        [
          324.5,
          418.0
        ],
        [
          325.5,
          419.0
        ],
        [
          324.5,
          420.0
        ],
        [
          324.5,
          426.0
        ],
        [
          321.5,
          429.0
        ],
        [
          321.5,
          430.0
        ],
        [
          319.0,
          432.5
        ],
        [
          318.0,
          432.5
        ],
        [
          314.5,
          436.0
        ],
        [
          314.5,
          437.0
        ],
        [
          312.5,
          439.0
        ],
        [
          312.5,
          440.0
        ],
        [
          308.0,
          444.5
        ],
        [
          307.0,
          444.5
        ],
        [
          305.5,
          446.0
        ],
        [
          305.5,
          447.0
        ],
        [
          304.5,
          448.0
        ],
        [
          304.5,
          449.0
        ],
        [
          304.0,
          449.5
        ],
        [
          303.0,
          449.5
        ],
        [
          301.5,
          451.0
        ],
        [
          301.5,
          452.0
        ],
        [
          300.5,
          453.0
        ],
        [
          300.5,
          454.0
        ],
        [
          299.5,
          455.0
        ],
        [
          299.5,
          456.0
        ]
      ],
      "group_id": null,
      "description": "",
      "shape_type": "polygon",
      "flags": {},
      "mask": null
    },
    {
      "label": "hand",
      "points": [
        [
          321.0,
          534.5
        ],
        [
          317.0,
          534.5
        ],
        [
          316.0,
          533.5
        ],
        [
          315.0,
          533.5
        ],
        [
          314.0,
          532.5
        ],
        [
          313.0,
          532.5
        ],
        [
          309.0,
          528.5
        ],
        [
          308.0,
          528.5
        ],
        [
          306.5,
          527.0
        ],
        [
          306.5,
          526.0
        ],
        [
          305.5,
          525.0
        ],
        [
          305.5,
          524.0
        ],
        [
          304.5,
          523.0
        ],
        [
          304.5,
          522.0
        ],
        [
          303.5,
          521.0
        ],
        [
          303.5,
          519.0
        ],
        [
          302.5,
          518.0
        ],
        [
          302.5,
          510.0
        ],
        [
          303.5,
          509.0
        ],
        [
          303.5,
          501.0
        ],
        [
          304.5,
          500.0
        ],
        [
          304.5,
          497.0
        ],
        [
          305.5,
          496.0
        ],
        [
          305.5,
          495.0
        ],
        [
          306.5,
          494.0
        ],
        [
          306.5,
          493.0
        ],
        [
          307.5,
          492.0
        ],
        [
          307.5,
          491.0
        ],
        [
          308.0,
          490.5
        ],
        [
          309.0,
          490.5
        ],
        [
          314.0,
          485.5
        ],
        [
          316.0,
          485.5
        ],
        [
          317.0,
          484.5
        ],
        [
          319.0,
          484.5
        ],
        [
          320.0,
          483.5
        ],
        [
          321.0,
          484.5
        ],
        [
          322.0,
          484.5
        ],
        [
          323.5,
          486.0
        ],
        [
          323.5,
          487.0
        ],
        [
          324.5,
          488.0
        ],
        [
          324.5,
          489.0
        ],
        [
          326.5,
          491.0
        ],
        [
          326.5,
          492.0
        ],
        [
          327.5,
          493.0
        ],
        [
          327.5,
          494.0
        ],
        [
          329.5,
          496.0
        ],
        [
          329.5,
          497.0
        ],
        [
          331.5,
          499.0
        ],
        [
          331.5,
          500.0
        ],
        [
          336.0,
          504.5
        ],
        [
          337.0,
          504.5
        ],
        [
          338.0,
          505.5
        ],
        [
          339.0,
          505.5
        ],
        [
          341.0,
          507.5
        ],
        [
          342.0,
          507.5
        ],
        [
          343.0,
          508.5
        ],
        [
          344.0,
          508.5
        ],
        [
          347.5,
          512.0
        ],
        [
          347.0,
          512.5
        ],
        [
          346.0,
          512.5
        ],
        [
          344.0,
          514.5
        ],
        [
          343.0,
          514.5
        ],
        [
          340.0,
          517.5
        ],
        [
          339.0,
          517.5
        ],
        [
          338.0,
          518.5
        ],
        [
          337.0,
          518.5
        ],
        [
          336.0,
          519.5
        ],
        [
          335.0,
          519.5
        ],
        [
          330.5,
          524.0
        ],
        [
          330.5,
          525.0
        ],
        [
          328.5,
          527.0
        ],
        [
          328.5,
          528.0
        ],
        [
          323.0,
          533.5
        ],
        [
          322.0,
          533.5
        ]
      ],
      "group_id": null,
      "description": "",
      "shape_type": "polygon",
      "flags": {},
      "mask": null
    }
  ],
  "imagePath": "0000.png",
  "imageData": null,
  "imageHeight": 768,
  "imageWidth": 768
}